BenbanfaXueLinuxZhongwenban/README.md
BenbanfaXueLinuxZhongwenban/__init__.py
BenbanfaXueLinuxZhongwenban/__main__.py
BenbanfaXueLinuxZhongwenban/file.epub
BenbanfaXueLinuxZhongwenban/index.html
BenbanfaXueLinuxZhongwenban/css/__init__.py
BenbanfaXueLinuxZhongwenban/css/annotations.css
BenbanfaXueLinuxZhongwenban/css/main.css
BenbanfaXueLinuxZhongwenban/css/normalize.css
BenbanfaXueLinuxZhongwenban/css/popup.css
BenbanfaXueLinuxZhongwenban/font/__init__.py
BenbanfaXueLinuxZhongwenban/font/fontello.eot
BenbanfaXueLinuxZhongwenban/font/fontello.svg
BenbanfaXueLinuxZhongwenban/font/fontello.ttf
BenbanfaXueLinuxZhongwenban/font/fontello.woff
BenbanfaXueLinuxZhongwenban/img/__init__.py
BenbanfaXueLinuxZhongwenban/img/annotator-glyph-sprite.png
BenbanfaXueLinuxZhongwenban/img/annotator-icon-sprite.png
BenbanfaXueLinuxZhongwenban/img/apple-touch-icon.png
BenbanfaXueLinuxZhongwenban/img/cancelfullscreen.png
BenbanfaXueLinuxZhongwenban/img/close.png
BenbanfaXueLinuxZhongwenban/img/fullscreen.png
BenbanfaXueLinuxZhongwenban/img/loader.gif
BenbanfaXueLinuxZhongwenban/img/menu-icon.png
BenbanfaXueLinuxZhongwenban/img/save.png
BenbanfaXueLinuxZhongwenban/img/saved.png
BenbanfaXueLinuxZhongwenban/img/settings-s.png
BenbanfaXueLinuxZhongwenban/img/settings.png
BenbanfaXueLinuxZhongwenban/img/star.png
BenbanfaXueLinuxZhongwenban/js/__init__.py
BenbanfaXueLinuxZhongwenban/js/epub.js
BenbanfaXueLinuxZhongwenban/js/epub.min.js
BenbanfaXueLinuxZhongwenban/js/epub.min.map
BenbanfaXueLinuxZhongwenban/js/hooks.min.js
BenbanfaXueLinuxZhongwenban/js/hooks.min.map
BenbanfaXueLinuxZhongwenban/js/reader.js
BenbanfaXueLinuxZhongwenban/js/reader.js.map
BenbanfaXueLinuxZhongwenban/js/reader.min.js
BenbanfaXueLinuxZhongwenban/js/reader.min.map
BenbanfaXueLinuxZhongwenban/js/hooks/__init__.py
BenbanfaXueLinuxZhongwenban/js/hooks/extensions/__init__.py
BenbanfaXueLinuxZhongwenban/js/hooks/extensions/highlight.js
BenbanfaXueLinuxZhongwenban/js/libs/__init__.py
benbanfa_xue_linux_zhongwenban-2024.3.2.0.dist-info/METADATA
benbanfa_xue_linux_zhongwenban-2024.3.2.0.dist-info/WHEEL
benbanfa_xue_linux_zhongwenban-2024.3.2.0.dist-info/entry_points.txt
benbanfa_xue_linux_zhongwenban-2024.3.2.0.dist-info/top_level.txt
benbanfa_xue_linux_zhongwenban-2024.3.2.0.dist-info/RECORD
